corex/__init__.py
corex/crawlex.py
corex/eXelion.py
corex/templax.py
eXelion-0.5.0.dist-info/LICENSE
eXelion-0.5.0.dist-info/METADATA
eXelion-0.5.0.dist-info/WHEEL
eXelion-0.5.0.dist-info/entry_points.txt
eXelion-0.5.0.dist-info/top_level.txt
eXelion-0.5.0.dist-info/RECORD
