Metadata-Version: 2.1
Name: eXelion
Version: 0.5.0
Summary: Tools for XXE/XEE Payloads and Crawling
Home-page: https://github.com/K3res/eXelion
Author: K3res
Classifier: Programming Language :: Python :: 3
Classifier: License :: OSI Approved :: MIT License
Classifier: Operating System :: OS Independent
Requires-Python: >=3.6
License-File: LICENSE
Requires-Dist: requests
Requires-Dist: beautifulsoup4
Requires-Dist: urllib3
Requires-Dist: colorama
